disoauther/__init__.py
disoauther/exceptions.py
disoauther-0.0.1.dist-info/WHEEL
disoauther-0.0.1.dist-info/METADATA
disoauther-0.0.1.dist-info/RECORD
